Metadata-Version: 2.1
Name: saicalculator
Version: 0.0.1
Summary: Calculator
Home-page: 
Author: Shankar Sai Ganesh
Author-email: shankarsaiganesh@gmail.com
License: MIT
Keywords: calculator
Platform: UNKNOWN
Classifier: Development Status :: 5 - Production/Stable
Classifier: Intended Audience :: Financial and Insurance Industry
Classifier: Operating System :: MacOS
Classifier: License :: OSI Approved :: MIT License
Classifier: Programming Language :: Python :: 3
License-File: LICENSE.txt
